SignalProcessingTools/__init__.py
SignalProcessingTools/__version__.py
SignalProcessingTools/space_signal.py
SignalProcessingTools/time_signal.py
signalprocessingtools-1.2.4.dist-info/METADATA
signalprocessingtools-1.2.4.dist-info/WHEEL
signalprocessingtools-1.2.4.dist-info/top_level.txt
signalprocessingtools-1.2.4.dist-info/RECORD
