Metadata-Version: 2.4
Name: SignalProcessingTools
Version: 1.2.4
Summary: Signal processing tools
Author: attr: SignalProcessingTools.__author__
Author-email: bruno.zuadacoelho@deltares.nl, aron.noordam@deltares.nl
Classifier: Programming Language :: Python :: 3
Classifier: License :: OSI Approved :: MIT License
Classifier: Operating System :: OS Independent
Requires-Python: >=3.10
Requires-Dist: matplotlib>=3.10
Requires-Dist: numpy>=2.2
Requires-Dist: scipy>=1.15
Provides-Extra: testing
Requires-Dist: pytest>=8.0; extra == "testing"
Requires-Dist: tox>=4.13; extra == "testing"
Requires-Dist: pre_commit>=4.2.0; extra == "testing"
